{
  "name": "normal",
  "width": 480,
  "height": 320,
  "default_font": "DejaVu Sans Mono",
  "default_font_size": 14,
  "default_color": "#f8fafc",
  "default_background": "#0b1220",
  "level_colors": [
    "#22c55e",
    "#eab308",
    "#f97316",
    "#ef4444"
  ],
  "default_thresholds": [
    25,
    50,
    75,
    100
  ],
  "output_types": ["memimg"],
  "refresh_interval": 1000,
  "history_size": 150,
  "custom_monitors": [],
  "items": [
    {
      "type": "simple_value",
      "edit_ui_name": "1_cpu_temp",
      "monitor": "go_native.cpu.temp",
      "unit": "auto",
      "x": 8,
      "y": 8,
      "width": 112,
      "height": 42,
      "font_size": 16,
      "bg": "#0f172a",
      "border_width": 1,
      "border_color": "#334155",
      "radius": 8
    },
    {
      "type": "simple_value",
      "edit_ui_name": "2_gpu_temp",
      "monitor": "gpu_temp",
      "unit": "auto",
      "x": 128,
      "y": 8,
      "width": 112,
      "height": 42,
      "font_size": 16,
      "bg": "#0f172a",
      "border_width": 1,
      "border_color": "#334155",
      "radius": 8
    },
    {
      "type": "simple_value",
      "edit_ui_name": "3_disk1_temp",
      "monitor": "go_native.disk.1.temp",
      "unit": "auto",
      "x": 248,
      "y": 8,
      "width": 112,
      "height": 42,
      "font_size": 16,
      "bg": "#0f172a",
      "border_width": 1,
      "border_color": "#334155",
      "radius": 8
    },
    {
      "type": "simple_value",
      "edit_ui_name": "4_net1_upload",
      "monitor": "go_native.net.1.upload",
      "unit": "auto",
      "x": 368,
      "y": 8,
      "width": 104,
      "height": 42,
      "font_size": 13,
      "bg": "#0f172a",
      "border_width": 1,
      "border_color": "#334155",
      "radius": 8
    },
    {
      "type": "simple_progress",
      "edit_ui_name": "5_cpu_usage",
      "monitor": "go_native.cpu.usage",
      "unit": "auto",
      "x": 8,
      "y": 58,
      "width": 228,
      "height": 34,
      "font_size": 13,
      "bg": "#1e293b",
      "border_width": 1,
      "border_color": "#334155",
      "radius": 8
    },
    {
      "type": "simple_progress",
      "edit_ui_name": "6_gpu_usage",
      "monitor": "gpu_usage",
      "unit": "auto",
      "x": 244,
      "y": 58,
      "width": 228,
      "height": 34,
      "font_size": 13,
      "bg": "#1e293b",
      "border_width": 1,
      "border_color": "#334155",
      "radius": 8
    },
    {
      "type": "simple_line_chart",
      "edit_ui_name": "7_cpu_chart",
      "monitor": "go_native.cpu.usage",
      "unit": "auto",
      "x": 8,
      "y": 100,
      "width": 228,
      "height": 90,
      "bg": "#0f172a",
      "border_width": 1,
      "border_color": "#334155",
      "radius": 8
    },
    {
      "type": "simple_line_chart",
      "edit_ui_name": "8_gpu_chart",
      "monitor": "gpu_usage",
      "unit": "auto",
      "x": 244,
      "y": 100,
      "width": 228,
      "height": 90,
      "bg": "#0f172a",
      "border_width": 1,
      "border_color": "#334155",
      "radius": 8
    },
    {
      "type": "simple_value",
      "edit_ui_name": "9_disk1_name",
      "monitor": "go_native.disk.1.name",
      "unit": "auto",
      "x": 8,
      "y": 198,
      "width": 228,
      "height": 34,
      "font_size": 12,
      "bg": "#0f172a",
      "border_width": 1,
      "border_color": "#334155",
      "radius": 8
    },
    {
      "type": "simple_value",
      "edit_ui_name": "10_disk1_size",
      "monitor": "go_native.disk.1.size",
      "unit": "auto",
      "x": 244,
      "y": 198,
      "width": 228,
      "height": 34,
      "font_size": 12,
      "bg": "#0f172a",
      "border_width": 1,
      "border_color": "#334155",
      "radius": 8
    },
    {
      "type": "simple_value",
      "edit_ui_name": "11_net1_ip",
      "monitor": "go_native.net.1.ip",
      "unit": "auto",
      "x": 8,
      "y": 240,
      "width": 306,
      "height": 34,
      "font_size": 12,
      "bg": "#0f172a",
      "border_width": 1,
      "border_color": "#334155",
      "radius": 8
    },
    {
      "type": "simple_value",
      "edit_ui_name": "12_current_time",
      "monitor": "go_native.system.current_time",
      "unit": "auto",
      "x": 322,
      "y": 240,
      "width": 150,
      "height": 34,
      "font_size": 12,
      "bg": "#0f172a",
      "border_width": 1,
      "border_color": "#334155",
      "radius": 8
    }
  ]
}
